LICENSE
README.md
setup.py
examples/__init__.py
examples/keyboard_bot.py
examples/keyboard_bot_test.py
examples/ping_bot.py
examples/ping_bot_test.py
maxgram/__init__.py
maxgram/api.py
maxgram/bot.py
maxgram/context.py
maxgram/keyboards.py
maxgram/types.py
maxgram.egg-info/PKG-INFO
maxgram.egg-info/SOURCES.txt
maxgram.egg-info/dependency_links.txt
maxgram.egg-info/requires.txt
maxgram.egg-info/top_level.txt
maxgram/core/__init__.py
maxgram/core/helpers/__init__.py
maxgram/core/network/__init__.py
maxgram/core/network/client.py
maxgram/core/network/polling.py