Metadata-Version: 2.4
Name: maxgram
Version: 0.1.4
Summary: Python client (unofficial) for MAX API. Early version
Home-page: https://github.com/kayumovru/maxgram
Author: Ruslan Kayumov
Author-email: kayumovru@gmail.com
Classifier: Programming Language :: Python :: 3
Classifier: License :: OSI Approved :: MIT License
Classifier: Operating System :: OS Independent
Requires-Python: >=3.8
License-File: LICENSE
Requires-Dist: requests>=2.31.0
Requires-Dist: pydantic>=2.6.0
Dynamic: author
Dynamic: author-email
Dynamic: classifier
Dynamic: description
Dynamic: description-content-type
Dynamic: home-page
Dynamic: license-file
Dynamic: requires-dist
Dynamic: requires-python
Dynamic: summary
